multiqc/__init__.py
multiqc/__main__.py
multiqc/multiqc.py
multiqc/modules/__init__.py
multiqc/modules/base_module.py
multiqc/modules/profile_runtime.py
multiqc/modules/software_versions.py
multiqc/modules/adapterremoval/__init__.py
multiqc/modules/adapterremoval/adapterremoval.py
multiqc/modules/afterqc/__init__.py
multiqc/modules/afterqc/afterqc.py
multiqc/modules/anglerfish/__init__.py
multiqc/modules/anglerfish/anglerfish.py
multiqc/modules/bakta/__init__.py
multiqc/modules/bakta/bakta.py
multiqc/modules/bamdst/__init__.py
multiqc/modules/bamdst/bamdst.py
multiqc/modules/bamtools/__init__.py
multiqc/modules/bamtools/bamtools.py
multiqc/modules/bamtools/stats.py
multiqc/modules/bbduk/__init__.py
multiqc/modules/bbduk/bbduk.py
multiqc/modules/bbmap/__init__.py
multiqc/modules/bbmap/bbmap.py
multiqc/modules/bbmap/bbmap_filetypes.py
multiqc/modules/bbmap/plot_aqhist.py
multiqc/modules/bbmap/plot_basic_hist.py
multiqc/modules/bbmap/plot_bhist.py
multiqc/modules/bbmap/plot_bqhist.py
multiqc/modules/bbmap/plot_covhist.py
multiqc/modules/bbmap/plot_idhist.py
multiqc/modules/bbmap/plot_ihist.py
multiqc/modules/bbmap/plot_indelhist.py
multiqc/modules/bbmap/plot_mhist.py
multiqc/modules/bbmap/plot_qahist.py
multiqc/modules/bbmap/plot_qchist.py
multiqc/modules/bbmap/plot_qhist.py
multiqc/modules/bcftools/__init__.py
multiqc/modules/bcftools/bcftools.py
multiqc/modules/bcftools/stats.py
multiqc/modules/bcl2fastq/__init__.py
multiqc/modules/bcl2fastq/bcl2fastq.py
multiqc/modules/bclconvert/__init__.py
multiqc/modules/bclconvert/bclconvert.py
multiqc/modules/biobambam2/__init__.py
multiqc/modules/biobambam2/biobambam2.py
multiqc/modules/biobloomtools/__init__.py
multiqc/modules/biobloomtools/biobloomtools.py
multiqc/modules/biscuit/__init__.py
multiqc/modules/biscuit/biscuit.py
multiqc/modules/bismark/__init__.py
multiqc/modules/bismark/bismark.py
multiqc/modules/bowtie1/__init__.py
multiqc/modules/bowtie1/bowtie1.py
multiqc/modules/bowtie2/__init__.py
multiqc_sgr-1.22.post0.dist-info/LICENSE
multiqc_sgr-1.22.post0.dist-info/METADATA
multiqc_sgr-1.22.post0.dist-info/WHEEL
multiqc_sgr-1.22.post0.dist-info/entry_points.txt
multiqc_sgr-1.22.post0.dist-info/top_level.txt
multiqc_sgr-1.22.post0.dist-info/RECORD
