Metadata-Version: 2.1
Name: multiqc_sgr
Version: 1.22.post0
Summary: Create aggregate bioinformatics analysis reports across many samples and tools
Author-email: Phil Ewels <phil.ewels@seqera.io>, Vlad Savelyev <vladislav.savelyev@seqera.io>
License: GNU GENERAL PUBLIC LICENSE
Project-URL: Homepage, https://multiqc.info
Project-URL: Repository, https://github.com/MultiQC/MultiQC
Project-URL: Issues, https://github.com/MultiQC/MultiQC/issues
Project-URL: Documentation, https://multiqc.info/docs
Project-URL: Changelog, https://github.com/MultiQC/MultiQC/blob/main/CHANGELOG.md
Keywords: bioinformatics,biology,sequencing,NGS,next generation sequencing,quality control
Classifier: Development Status :: 5 - Production/Stable
Classifier: Environment :: Console
Classifier: Environment :: Web Environment
Classifier: Intended Audience :: Science/Research
Classifier: License :: OSI Approved :: GNU General Public License v3 (GPLv3)
Classifier: Natural Language :: English
Classifier: Operating System :: MacOS :: MacOS X
Classifier: Operating System :: POSIX
Classifier: Operating System :: Unix
Classifier: Programming Language :: Python
Classifier: Programming Language :: JavaScript
Classifier: Topic :: Scientific/Engineering
Classifier: Topic :: Scientific/Engineering :: Bio-Informatics
Classifier: Topic :: Scientific/Engineering :: Visualization
Requires-Python: >=3.8
License-File: LICENSE
Requires-Dist: click
Requires-Dist: coloredlogs
Requires-Dist: humanize
Requires-Dist: importlib-metadata
Requires-Dist: jinja2 >=3.0.0
Requires-Dist: kaleido
Requires-Dist: markdown
Requires-Dist: numpy
Requires-Dist: packaging
Requires-Dist: requests
Requires-Dist: Pillow >=10
Requires-Dist: plotly >=5.18
Requires-Dist: pyyaml >=4
Requires-Dist: pyaml-env
Requires-Dist: rich >=10
Requires-Dist: rich-click
Requires-Dist: spectra >=0.0.10
Provides-Extra: dev
Requires-Dist: pre-commit ; extra == 'dev'
Requires-Dist: ruff ; extra == 'dev'
